[
  {
    "filename": "4_163.png",
    "reason": "too many contours",
    "too": 4
  },
  {
    "filename": "9_68.png",
    "reason": "too many contours",
    "too": 4
  },
  {
    "filename": "A_32.png",
    "reason": "too many contours",
    "too": 4
  },
  {
    "filename": "A_33.png",
    "reason": "too many contours",
    "too": 4
  },
  {
    "filename": "M_135.png",
    "reason": "too many contours",
    "too": 5
  },
  {
    "filename": "P_152.png",
    "reason": "too many contours",
    "too": 4
  },
  {
    "filename": "Q_127.png",
    "reason": "too many contours",
    "too": 4
  },
  {
    "filename": "Q_129.png",
    "reason": "too many contours",
    "too": 4
  },
  {
    "filename": "S_140.png",
    "reason": "too many contours",
    "too": 5
  },
  {
    "filename": "W_119.png",
    "reason": "too many contours",
    "too": 4
  },
  {
    "filename": "Y_118.png",
    "reason": "too many contours",
    "too": 4
  }
]